{"data":{"items":[{"content":"{\"text\":\"量变达到质变了。很好哦~\\n从拙力到心力的转变，是线条质量的一个分水岭。心力驱动下的手部运动会更加的稳健柔和，力量却更有渗透力。\",\"hasMore\":false,\"images\":[],\"imageTotalCount\":0,\"audios\":[],\"audioTotalCount\":0}","createdTime":"2022-06-30T21:49:11+0800","evaluateStatus":1,"id":11164811,"userInfo":{"avatar":"https://cc.hjfile.cn/cc/img/20220602/2022060208442182070043.jpg","ccUserName":"jnukant001","identity":1,"nickName":"一定写好字吖","userId":151885219},"userPower":0},{"content":"{\"text\":\"谢谢老师每次的点评都言近旨远～\\n简直是醍醐灌顶～\\n我继续努力～\",\"hasMore\":false}","createdTime":"2022-06-30T21:58:24+0800","evaluateStatus":0,"id":11164777,"parentUserInfo":{"avatar":"https://cc.hjfile.cn/cc/img/20220602/2022060208442182070043.jpg","ccUserName":"jnukant001","identity":1,"nickName":"一定写好字吖","userId":151885219},"userInfo":{"avatar":"https://cc.hjfile.cn/cc/img/20220602/2022060211000719416088.jpg","ccUserName":"拼命姑娘5t","identity":2,"nickName":"乐也屋子","userId":33883859},"userPower":0}],"nextPage":false},"message":"success","status":0}