{"data":{"items":[{"content":"{\"text\":\"不敢当，不敢当！只是早一点开始学而已！\",\"hasMore\":false}","createdTime":"2022-11-26T22:28:34+0800","evaluateStatus":0,"id":12049936,"parentUserInfo":{"avatar":"https://cc.hjfile.cn/cc/img/20231028/2023102801220220683569.jpg","ccUserName":"宅小星","identity":0,"nickName":"小星星","userId":13649940},"userInfo":{"avatar":"https://cc.hjfile.cn/cc/img/20230521/2023052105165190371834.jpg","ccUserName":"手机用户1949chtdt","identity":2,"nickName":"饮川【0138】","userId":158992173},"userPower":0},{"content":"{\"text\":\"大佬受我一拜哈哈哈\",\"hasMore\":false}","createdTime":"2022-11-26T21:56:51+0800","evaluateStatus":0,"id":12049816,"userInfo":{"avatar":"https://cc.hjfile.cn/cc/img/20231028/2023102801220220683569.jpg","ccUserName":"宅小星","identity":0,"nickName":"小星星","userId":13649940},"userPower":0}],"nextPage":false},"message":"success","status":0}