{"data":{"items":[{"content":"{\"text\":\"线条很稳！真棒！\",\"hasMore\":false}","createdTime":"2022-12-04T23:27:18+0800","evaluateStatus":0,"id":12091524,"userInfo":{"avatar":"https://cc.hjfile.cn/cc/img/20231028/2023102801220220683569.jpg","ccUserName":"宅小星","identity":0,"nickName":"小星星","userId":13649940},"userPower":0},{"content":"{\"text\":\"看着真舒服呀哈哈\",\"hasMore\":false}","createdTime":"2022-12-04T23:09:21+0800","evaluateStatus":0,"id":12091344,"userInfo":{"avatar":"https://cc.hjfile.cn/cc/img/20230218/2023021810071470754282.jpg","ccUserName":"手机用户4441yzfpt","identity":0,"nickName":"狐萝卜【0306】","userId":162570935},"userPower":0},{"content":"{\"text\":\"真的太优秀了！\",\"hasMore\":false}","createdTime":"2022-12-04T21:47:22+0800","evaluateStatus":0,"id":12090465,"userInfo":{"avatar":"https://i2n.hjfile.cn/u/default/ext/200/11.jpg","ccUserName":"手机用户6049iearx","identity":0,"nickName":"喵喵妙也0312","userId":162622304},"userPower":0},{"content":"{\"text\":\"第一遍就这么过分优秀了\",\"hasMore\":false}","createdTime":"2022-12-04T21:17:52+0800","evaluateStatus":0,"id":12090326,"userInfo":{"avatar":"https://cc.hjfile.cn/cc/img/20220602/2022060211000719416088.jpg","ccUserName":"拼命姑娘5t","identity":2,"nickName":"乐也屋子","userId":33883859},"userPower":0}],"nextPage":false},"message":"success","status":0}