{"data":{"items":[{"content":"{\"text\":\"这些字都是我之前精临过的，明天继续开始精临\",\"hasMore\":false}","createdTime":"2022-12-15T23:00:59+0800","evaluateStatus":0,"id":12141874,"parentUserInfo":{"avatar":"https://cc.hjfile.cn/cc/img/20230521/2023052105165190371834.jpg","ccUserName":"手机用户1949chtdt","identity":2,"nickName":"饮川【0138】","userId":158992173},"userInfo":{"avatar":"https://cc.hjfile.cn/cc/img/20220602/2022060211011010311044.jpg","ccUserName":"手机用户8305iudbw","identity":0,"nickName":"今天航海【0069】","userId":157711978},"userPower":0},{"content":"{\"text\":\"不敢当\",\"hasMore\":false}","createdTime":"2022-12-15T23:00:32+0800","evaluateStatus":0,"id":12141974,"parentUserInfo":{"avatar":"https://i2n.hjfile.cn/u/default/ext/200/11.jpg","ccUserName":"手机用户6049iearx","identity":0,"nickName":"喵喵妙也0312","userId":162622304},"userInfo":{"avatar":"https://cc.hjfile.cn/cc/img/20220602/2022060211011010311044.jpg","ccUserName":"手机用户8305iudbw","identity":0,"nickName":"今天航海【0069】","userId":157711978},"userPower":0},{"content":"{\"text\":\"加油(҂˘̀^˘́)ง通临之前老师让我精临单字，你也可以试试，精临到能一遍就写好没写过的字\",\"hasMore\":false}","createdTime":"2022-12-15T22:40:13+0800","evaluateStatus":0,"id":12141928,"userInfo":{"avatar":"https://cc.hjfile.cn/cc/img/20230521/2023052105165190371834.jpg","ccUserName":"手机用户1949chtdt","identity":2,"nickName":"饮川【0138】","userId":158992173},"userPower":0},{"content":"{\"text\":\"仰望大佬\",\"hasMore\":false}","createdTime":"2022-12-15T21:52:40+0800","evaluateStatus":0,"id":12141583,"userInfo":{"avatar":"https://i2n.hjfile.cn/u/default/ext/200/11.jpg","ccUserName":"手机用户6049iearx","identity":0,"nickName":"喵喵妙也0312","userId":162622304},"userPower":0},{"content":"{\"text\":\"谢谢鼓励，一起加油\",\"hasMore\":false}","createdTime":"2022-12-15T21:22:13+0800","evaluateStatus":0,"id":12141257,"parentUserInfo":{"avatar":"https://cc.hjfile.cn/cc/img/20230218/2023021810071470754282.jpg","ccUserName":"手机用户4441yzfpt","identity":0,"nickName":"狐萝卜【0306】","userId":162570935},"userInfo":{"avatar":"https://cc.hjfile.cn/cc/img/20220602/2022060211011010311044.jpg","ccUserName":"手机用户8305iudbw","identity":0,"nickName":"今天航海【0069】","userId":157711978},"userPower":0},{"content":"{\"text\":\"你也很棒哈哈哈哈 牛牛的\",\"hasMore\":false}","createdTime":"2022-12-15T20:35:06+0800","evaluateStatus":0,"id":12140894,"userInfo":{"avatar":"https://cc.hjfile.cn/cc/img/20230218/2023021810071470754282.jpg","ccUserName":"手机用户4441yzfpt","identity":0,"nickName":"狐萝卜【0306】","userId":162570935},"userPower":0}],"nextPage":false},"message":"success","status":0}