{"data":{"items":[{"content":"{\"text\":\"写的真好！\",\"hasMore\":false}","createdTime":"2023-02-22T22:45:10+0800","evaluateStatus":0,"id":12384039,"userInfo":{"avatar":"https://cc.hjfile.cn/cc/img/20220717/2022071703010279323748.jpg","ccUserName":"手机用户3441pjcvc","identity":0,"nickName":"Narwal-0128","userId":121264437},"userPower":0},{"content":"{\"text\":\"美美美\",\"hasMore\":false}","createdTime":"2023-02-22T14:35:25+0800","evaluateStatus":0,"id":12381961,"userInfo":{"avatar":"https://cc.hjfile.cn/cc/img/20220602/2022060211000719416088.jpg","ccUserName":"拼命姑娘5t","identity":2,"nickName":"乐也屋子","userId":33883859},"userPower":0},{"content":"{\"text\":\"可以说是相当丝滑了～\",\"hasMore\":false}","createdTime":"2023-02-22T14:04:48+0800","evaluateStatus":0,"id":12381887,"userInfo":{"avatar":"https://cc.hjfile.cn/cc/img/20230218/2023021810071470754282.jpg","ccUserName":"手机用户4441yzfpt","identity":0,"nickName":"狐萝卜【0306】","userId":162570935},"userPower":0},{"content":"{\"text\":\"这弧线太美了\",\"hasMore\":false}","createdTime":"2023-02-22T13:35:27+0800","evaluateStatus":0,"id":12381824,"userInfo":{"avatar":"https://cc.hjfile.cn/cc/img/20230125/2023012512122794335945.jpg","ccUserName":"手机用户3359ervpb","identity":0,"nickName":"雅莉0417","userId":163910582},"userPower":0}],"nextPage":false},"message":"success","status":0}