{"data":{"items":[{"content":"{\"text\":\"纸的问题？还是润笔时水分没擦干？\",\"hasMore\":false}","createdTime":"2023-04-09T17:16:05+0800","evaluateStatus":0,"id":12586895,"parentUserInfo":{"avatar":"https://cc.hjfile.cn/cc/img/20230416/202304161110486138179.jpg","ccUserName":"uejdru","identity":0,"nickName":"半夏 0497","userId":112577014},"userInfo":{"avatar":"https://cc.hjfile.cn/cc/img/20230304/2023030409511091555597.jpg","ccUserName":"手机用户0395cxgzw","identity":0,"nickName":"谢喻生【439】","userId":163968681},"userPower":0},{"content":"{\"text\":\"老师推荐的\",\"hasMore\":false}","createdTime":"2023-04-08T21:54:10+0800","evaluateStatus":0,"id":12584492,"parentUserInfo":{"avatar":"https://cc.hjfile.cn/cc/img/20230304/2023030409511091555597.jpg","ccUserName":"手机用户0395cxgzw","identity":0,"nickName":"谢喻生【439】","userId":163968681},"userInfo":{"avatar":"https://cc.hjfile.cn/cc/img/20230416/202304161110486138179.jpg","ccUserName":"uejdru","identity":0,"nickName":"半夏 0497","userId":112577014},"userPower":0},{"content":"{\"text\":\"我站在左边，然后人是斜的(\",\"hasMore\":false}","createdTime":"2023-04-08T21:26:18+0800","evaluateStatus":0,"id":12584417,"parentUserInfo":{"avatar":"https://cc.hjfile.cn/cc/img/20230304/2023030409190901770976.jpg","ccUserName":"手机用户7218jwawe","identity":0,"nickName":"讲文明院长【0503】","userId":164237175},"userInfo":{"avatar":"https://cc.hjfile.cn/cc/img/20230304/2023030409511091555597.jpg","ccUserName":"手机用户0395cxgzw","identity":0,"nickName":"谢喻生【439】","userId":163968681},"userPower":0},{"content":"{\"text\":\"用的什么墨呀\",\"hasMore\":false}","createdTime":"2023-04-08T21:25:49+0800","evaluateStatus":0,"id":12584416,"parentUserInfo":{"avatar":"https://cc.hjfile.cn/cc/img/20230416/202304161110486138179.jpg","ccUserName":"uejdru","identity":0,"nickName":"半夏 0497","userId":112577014},"userInfo":{"avatar":"https://cc.hjfile.cn/cc/img/20230304/2023030409511091555597.jpg","ccUserName":"手机用户0395cxgzw","identity":0,"nickName":"谢喻生【439】","userId":163968681},"userPower":0},{"content":"{\"text\":\"为啥你们的墨迹都是那么黑，我的干了之后却是灰黑色呢？真的是力道没到位吗？\",\"hasMore\":false}","createdTime":"2023-04-08T21:15:47+0800","evaluateStatus":0,"id":12584285,"userInfo":{"avatar":"https://cc.hjfile.cn/cc/img/20230416/202304161110486138179.jpg","ccUserName":"uejdru","identity":0,"nickName":"半夏 0497","userId":112577014},"userPower":0},{"content":"{\"text\":\"我总是站斜了\",\"hasMore\":false}","createdTime":"2023-04-08T13:51:10+0800","evaluateStatus":0,"id":12583173,"parentUserInfo":{"avatar":"https://cc.hjfile.cn/cc/img/20230304/2023030409511091555597.jpg","ccUserName":"手机用户0395cxgzw","identity":0,"nickName":"谢喻生【439】","userId":163968681},"userInfo":{"avatar":"https://cc.hjfile.cn/cc/img/20230304/2023030409190901770976.jpg","ccUserName":"手机用户7218jwawe","identity":0,"nickName":"讲文明院长【0503】","userId":164237175},"userPower":0},{"content":"{\"text\":\"可能是我大臂没转过来，头还是斜着的。\",\"hasMore\":false}","createdTime":"2023-04-08T12:32:32+0800","evaluateStatus":0,"id":12583064,"parentUserInfo":{"avatar":"https://cc.hjfile.cn/cc/img/20231020/2023102006580863363416.jpg","ccUserName":"手机用户2873nyhgj","identity":0,"nickName":"東南隅【0530】","userId":164418225},"userInfo":{"avatar":"https://cc.hjfile.cn/cc/img/20230304/2023030409511091555597.jpg","ccUserName":"手机用户0395cxgzw","identity":0,"nickName":"谢喻生【439】","userId":163968681},"userPower":0},{"content":"{\"text\":\"我有时候写到最后头低了，线就会歪。\",\"hasMore\":false}","createdTime":"2023-04-08T12:29:27+0800","evaluateStatus":0,"id":12583058,"userInfo":{"avatar":"https://cc.hjfile.cn/cc/img/20231020/2023102006580863363416.jpg","ccUserName":"手机用户2873nyhgj","identity":0,"nickName":"東南隅【0530】","userId":164418225},"userPower":0}],"nextPage":false},"message":"success","status":0}