{"data":{"items":[{"content":"{\"text\":\"最近作业＋考试还有早八(๑˙ー˙๑)\",\"hasMore\":false}","createdTime":"2023-06-07T22:56:54+0800","evaluateStatus":0,"id":12805544,"parentUserInfo":{"avatar":"https://i2n.hjfile.cn/u/200/133276406/9b72403ba54c47f.jpg","ccUserName":"陈秋杏2jdg6","identity":0,"nickName":"陈秋杏","userId":133276406},"userInfo":{"avatar":"https://cc.hjfile.cn/cc/img/20230304/2023030409190901770976.jpg","ccUserName":"手机用户7218jwawe","identity":0,"nickName":"讲文明院长【0503】","userId":164237175},"userPower":0},{"content":"{\"text\":\"最近院长不早起打卡啦\",\"hasMore\":false}","createdTime":"2023-06-07T22:07:47+0800","evaluateStatus":0,"id":12805090,"userInfo":{"avatar":"https://i2n.hjfile.cn/u/200/133276406/9b72403ba54c47f.jpg","ccUserName":"陈秋杏2jdg6","identity":0,"nickName":"陈秋杏","userId":133276406},"userPower":0}],"nextPage":false},"message":"success","status":0}