{"data":{"items":[{"content":"{\"text\":\"az，打错字了，“含金量”\",\"hasMore\":false}","createdTime":"2023-07-05T16:01:09+0800","evaluateStatus":0,"id":12889238,"parentUserInfo":{"avatar":"https://cc.hjfile.cn/cc/img/20230310/2023031003143274056544.jpg","ccUserName":"手机用户8154ptkqm","identity":0,"nickName":"小王【0578】","userId":164737723},"userInfo":{"avatar":"https://cc.hjfile.cn/cc/img/20230304/2023030409511091555597.jpg","ccUserName":"手机用户0395cxgzw","identity":0,"nickName":"谢喻生【439】","userId":163968681},"userPower":0},{"content":"{\"text\":\"法学牲：懂不懂学校守门人的回家了啊（战术后仰）\",\"hasMore\":false}","createdTime":"2023-07-04T20:54:18+0800","evaluateStatus":0,"id":12886481,"parentUserInfo":{"avatar":"https://cc.hjfile.cn/cc/img/20230310/2023031003143274056544.jpg","ccUserName":"手机用户8154ptkqm","identity":0,"nickName":"小王【0578】","userId":164737723},"userInfo":{"avatar":"https://cc.hjfile.cn/cc/img/20230304/2023030409511091555597.jpg","ccUserName":"手机用户0395cxgzw","identity":0,"nickName":"谢喻生【439】","userId":163968681},"userPower":0},{"content":"{\"text\":\"六月十三一，给你个大拇哥\",\"hasMore\":false}","createdTime":"2023-07-04T13:06:29+0800","evaluateStatus":0,"id":12885438,"userInfo":{"avatar":"https://cc.hjfile.cn/cc/img/20231020/2023102006580863363416.jpg","ccUserName":"手机用户2873nyhgj","identity":0,"nickName":"東南隅【0530】","userId":164418225},"userPower":0},{"content":"{\"text\":\"小谢怎么还没放假\",\"hasMore\":false}","createdTime":"2023-07-04T12:49:11+0800","evaluateStatus":0,"id":12885359,"userInfo":{"avatar":"https://cc.hjfile.cn/cc/img/20230310/2023031003143274056544.jpg","ccUserName":"手机用户8154ptkqm","identity":0,"nickName":"小王【0578】","userId":164737723},"userPower":0}],"nextPage":false},"message":"success","status":0}