{"data":{"items":[{"content":"{\"text\":\"一起加油！！\",\"hasMore\":false}","createdTime":"2023-09-05T14:52:26+0800","evaluateStatus":0,"id":13154478,"parentUserInfo":{"avatar":"https://cc.hjfile.cn/cc/img/20231109/2023110909331609345775.jpg","ccUserName":"字浅","identity":0,"nickName":"子静 1067","userId":168704630},"userInfo":{"avatar":"https://cc.hjfile.cn/cc/img/20231020/2023102006580863363416.jpg","ccUserName":"手机用户2873nyhgj","identity":0,"nickName":"東南隅【0530】","userId":164418225},"userPower":0},{"content":"{\"text\":\"后来者的榜样！赞\",\"hasMore\":false}","createdTime":"2023-09-05T11:28:29+0800","evaluateStatus":0,"id":13154006,"userInfo":{"avatar":"https://cc.hjfile.cn/cc/img/20231109/2023110909331609345775.jpg","ccUserName":"字浅","identity":0,"nickName":"子静 1067","userId":168704630},"userPower":0},{"content":"{\"text\":\"是的安歌，是墨碟的盖子\",\"hasMore\":false}","createdTime":"2023-09-05T09:34:46+0800","evaluateStatus":0,"id":13153701,"parentUserInfo":{"avatar":"https://i2n.hjfile.cn/u/200/166032939/6abd86e4b52a408.jpg","ccUserName":"手机用户2140gfqva","identity":0,"nickName":"楚安歌","userId":166032939},"userInfo":{"avatar":"https://cc.hjfile.cn/cc/img/20231020/2023102006580863363416.jpg","ccUserName":"手机用户2873nyhgj","identity":0,"nickName":"東南隅【0530】","userId":164418225},"userPower":0},{"content":"{\"text\":\"真厉害啊主任能不能教教我(°ー°〃)\",\"hasMore\":false}","createdTime":"2023-09-05T08:45:05+0800","evaluateStatus":0,"id":13153470,"userInfo":{"avatar":"https://cc.hjfile.cn/cc/img/20230312/2023031208242014075300.jpg","ccUserName":"手机用户0496viktz","identity":0,"nickName":"太阳当空赵【0464】","userId":154250449},"userPower":0},{"content":"{\"text\":\"主任的硬笔真好看啊～\",\"hasMore\":false}","createdTime":"2023-09-05T08:25:52+0800","evaluateStatus":0,"id":13153515,"userInfo":{"avatar":"https://cc.hjfile.cn/cc/img/20230918/2023091809403600680306.jpg","ccUserName":"张小旭vkqsn","identity":0,"nickName":"张小旭【0696】","userId":145666282},"userPower":0}],"nextPage":false},"message":"success","status":0}