{"data":{"items":[{"content":"{\"text\":\"越写越精神\",\"hasMore\":false}","createdTime":"2023-10-19T12:14:03+0800","evaluateStatus":0,"id":13312310,"userInfo":{"avatar":"https://cc.hjfile.cn/cc/img/20231024/2023102401502466126073.jpg","ccUserName":"而归儿","identity":2,"nickName":"而归【0087】","userId":158130835},"userPower":0},{"content":"{\"text\":\"快乐的感觉\",\"hasMore\":false}","createdTime":"2023-10-19T09:25:05+0800","evaluateStatus":0,"id":13311805,"userInfo":{"avatar":"https://cc.hjfile.cn/cc/img/20231207/2023120706310930817114.jpg","ccUserName":"JayenLoo","identity":0,"nickName":"知临1140","userId":11026376},"userPower":0},{"content":"{\"text\":\"清醒的感觉\",\"hasMore\":false}","createdTime":"2023-10-19T09:21:16+0800","evaluateStatus":0,"id":13311600,"userInfo":{"avatar":"https://cc.hjfile.cn/cc/img/20231206/2023120610342812690403.jpg","ccUserName":"手机用户1431jssjb","identity":0,"nickName":"七月瑾【1098】","userId":169246489},"userPower":0},{"content":"{\"text\":\"啊啊啊啊啊啊啊啊啊啊啊啊啊我也想要自由\",\"hasMore\":false}","createdTime":"2023-10-19T08:18:41+0800","evaluateStatus":0,"id":13311535,"parentUserInfo":{"avatar":"https://cc.hjfile.cn/cc/img/20231020/2023102006580863363416.jpg","ccUserName":"手机用户2873nyhgj","identity":0,"nickName":"東南隅【0530】","userId":164418225},"userInfo":{"avatar":"https://cc.hjfile.cn/cc/img/20230312/2023031208242014075300.jpg","ccUserName":"手机用户0496viktz","identity":0,"nickName":"太阳当空赵【0464】","userId":154250449},"userPower":0}],"nextPage":false},"message":"success","status":0}