{"data":{"items":[{"content":"{\"text\":\"厉害厉害\",\"hasMore\":false}","createdTime":"2023-10-31T22:03:01+0800","evaluateStatus":0,"id":13360250,"userInfo":{"avatar":"https://cc.hjfile.cn/cc/img/20231027/2023102711485766647693.jpg","ccUserName":"手机用户4073xghhq","identity":0,"nickName":"阿龙【1168】","userId":135682899},"userPower":0},{"content":"{\"text\":\"加油！很快你也可以\",\"hasMore\":false}","createdTime":"2023-10-31T20:11:42+0800","evaluateStatus":0,"id":13359933,"parentUserInfo":{"avatar":"https://i2n.hjfile.cn/u/200/169944988/4f7fe75bda8c4a5.jpg","ccUserName":"张亮sktkf","identity":0,"nickName":"空谷幽竹【1156】","userId":169944988},"userInfo":{"avatar":"https://cc.hjfile.cn/cc/img/20231008/2023100809303264771696.jpg","ccUserName":"Erin张jfq72","identity":0,"nickName":"风起 1087","userId":168979112},"userPower":0},{"content":"{\"text\":\"这线条真好看，墨色很饱满\",\"hasMore\":false}","createdTime":"2023-10-31T20:00:49+0800","evaluateStatus":0,"id":13359829,"userInfo":{"avatar":"https://i2n.hjfile.cn/u/200/169944988/4f7fe75bda8c4a5.jpg","ccUserName":"张亮sktkf","identity":0,"nickName":"空谷幽竹【1156】","userId":169944988},"userPower":0}],"nextPage":false},"message":"success","status":0}