{"data":{"items":[{"content":"{\"text\":\"和其他人比就完全不行了╥﹏╥\",\"hasMore\":false}","createdTime":"2023-11-14T22:14:27+0800","evaluateStatus":0,"id":13412797,"parentUserInfo":{"avatar":"https://cc.hjfile.cn/cc/img/20231113/202311131058142767377.jpg","ccUserName":"南方之羽","identity":0,"nickName":"南羽【1141】","userId":169818032},"userInfo":{"avatar":"https://cc.hjfile.cn/cc/img/20230304/2023030409511091555597.jpg","ccUserName":"手机用户0395cxgzw","identity":0,"nickName":"谢喻生【439】","userId":163968681},"userPower":0},{"content":"{\"text\":\"好棒呀\",\"hasMore\":false}","createdTime":"2023-11-14T21:13:28+0800","evaluateStatus":0,"id":13412554,"userInfo":{"avatar":"https://cc.hjfile.cn/cc/img/20231113/202311131058142767377.jpg","ccUserName":"南方之羽","identity":0,"nickName":"南羽【1141】","userId":169818032},"userPower":0}],"nextPage":false},"message":"success","status":0}