{"data":{"items":[{"content":"{\"text\":\"这样啊，感觉自己一直不会的\",\"hasMore\":false}","createdTime":"2023-12-20T21:34:26+0800","evaluateStatus":0,"id":13546982,"parentUserInfo":{"avatar":"https://cc.hjfile.cn/cc/img/20220709/2022070906010836982765.jpg","ccUserName":"筱杭","identity":2,"nickName":"筱杭（0115）","userId":9809486},"userInfo":{"avatar":"https://thirdwx.qlogo.cn/mmopen/vi_32/POgEwh4mIHO4nibH0KlMECNjjGxQUq24ZEaGT4poC6icRiccVGKSyXwibcPq4BWmiaIGuG1icwxaQX6grC9VemZoJ8rg/132","ccUserName":"手机用户8492hfwtb","identity":0,"nickName":"微信用户","userId":162463524},"userPower":0},{"content":"{\"text\":\"我的起笔还不行\\n去群里看老师的起笔视频 跟着练就可以了\",\"hasMore\":false}","createdTime":"2023-12-20T21:33:19+0800","evaluateStatus":0,"id":13546979,"parentUserInfo":{"avatar":"https://thirdwx.qlogo.cn/mmopen/vi_32/POgEwh4mIHO4nibH0KlMECNjjGxQUq24ZEaGT4poC6icRiccVGKSyXwibcPq4BWmiaIGuG1icwxaQX6grC9VemZoJ8rg/132","ccUserName":"手机用户8492hfwtb","identity":0,"nickName":"微信用户","userId":162463524},"userInfo":{"avatar":"https://cc.hjfile.cn/cc/img/20220709/2022070906010836982765.jpg","ccUserName":"筱杭","identity":2,"nickName":"筱杭（0115）","userId":9809486},"userPower":0},{"content":"{\"text\":\"厉害，请问起笔怎么搞啊\",\"hasMore\":false}","createdTime":"2023-12-20T21:31:10+0800","evaluateStatus":0,"id":13546969,"userInfo":{"avatar":"https://thirdwx.qlogo.cn/mmopen/vi_32/POgEwh4mIHO4nibH0KlMECNjjGxQUq24ZEaGT4poC6icRiccVGKSyXwibcPq4BWmiaIGuG1icwxaQX6grC9VemZoJ8rg/132","ccUserName":"手机用户8492hfwtb","identity":0,"nickName":"微信用户","userId":162463524},"userPower":0}],"nextPage":false},"message":"success","status":0}